{
  "order_details": [
    {
      "PutRequest": {
        "Item": {
          "order_id": {
            "N": "10646"
          },
          "product_id": {
            "N": "77"
          },
          "unit_price": {
            "N": "13.0"
          },
          "quantity": {
            "N": "35"
          },
          "discount": {
            "N": "0.25"
          }
        }
      }
    },
    {
      "PutRequest": {
        "Item": {
          "order_id": {
            "N": "10647"
          },
          "product_id": {
            "N": "19"
          },
          "unit_price": {
            "N": "9.19999981"
          },
          "quantity": {
            "N": "30"
          },
          "discount": {
            "N": "0.0"
          }
        }
      }
    },
    {
      "PutRequest": {
        "Item": {
          "order_id": {
            "N": "10647"
          },
          "product_id": {
            "N": "39"
          },
          "unit_price": {
            "N": "18.0"
          },
          "quantity": {
            "N": "20"
          },
          "discount": {
            "N": "0.0"
          }
        }
      }
    },
    {
      "PutRequest": {
        "Item": {
          "order_id": {
            "N": "10648"
          },
          "product_id": {
            "N": "22"
          },
          "unit_price": {
            "N": "21.0"
          },
          "quantity": {
            "N": "15"
          },
          "discount": {
            "N": "0.0"
          }
        }
      }
    },
    {
      "PutRequest": {
        "Item": {
          "order_id": {
            "N": "10648"
          },
          "product_id": {
            "N": "24"
          },
          "unit_price": {
            "N": "4.5"
          },
          "quantity": {
            "N": "15"
          },
          "discount": {
            "N": "0.150000006"
          }
        }
      }
    },
    {
      "PutRequest": {
        "Item": {
          "order_id": {
            "N": "10649"
          },
          "product_id": {
            "N": "28"
          },
          "unit_price": {
            "N": "45.5999985"
          },
          "quantity": {
            "N": "20"
          },
          "discount": {
            "N": "0.0"
          }
        }
      }
    },
    {
      "PutRequest": {
        "Item": {
          "order_id": {
            "N": "10649"
          },
          "product_id": {
            "N": "72"
          },
          "unit_price": {
            "N": "34.7999992"
          },
          "quantity": {
            "N": "15"
          },
          "discount": {
            "N": "0.0"
          }
        }
      }
    },
    {
      "PutRequest": {
        "Item": {
          "order_id": {
            "N": "10650"
          },
          "product_id": {
            "N": "30"
          },
          "unit_price": {
            "N": "25.8899994"
          },
          "quantity": {
            "N": "30"
          },
          "discount": {
            "N": "0.0"
          }
        }
      }
    },
    {
      "PutRequest": {
        "Item": {
          "order_id": {
            "N": "10650"
          },
          "product_id": {
            "N": "53"
          },
          "unit_price": {
            "N": "32.7999992"
          },
          "quantity": {
            "N": "25"
          },
          "discount": {
            "N": "0.0500000007"
          }
        }
      }
    },
    {
      "PutRequest": {
        "Item": {
          "order_id": {
            "N": "10650"
          },
          "product_id": {
            "N": "54"
          },
          "unit_price": {
            "N": "7.44999981"
          },
          "quantity": {
            "N": "30"
          },
          "discount": {
            "N": "0.0"
          }
        }
      }
    },
    {
      "PutRequest": {
        "Item": {
          "order_id": {
            "N": "10651"
          },
          "product_id": {
            "N": "19"
          },
          "unit_price": {
            "N": "9.19999981"
          },
          "quantity": {
            "N": "12"
          },
          "discount": {
            "N": "0.25"
          }
        }
      }
    },
    {
      "PutRequest": {
        "Item": {
          "order_id": {
            "N": "10651"
          },
          "product_id": {
            "N": "22"
          },
          "unit_price": {
            "N": "21.0"
          },
          "quantity": {
            "N": "20"
          },
          "discount": {
            "N": "0.25"
          }
        }
      }
    },
    {
      "PutRequest": {
        "Item": {
          "order_id": {
            "N": "10652"
          },
          "product_id": {
            "N": "30"
          },
          "unit_price": {
            "N": "25.8899994"
          },
          "quantity": {
            "N": "2"
          },
          "discount": {
            "N": "0.25"
          }
        }
      }
    },
    {
      "PutRequest": {
        "Item": {
          "order_id": {
            "N": "10652"
          },
          "product_id": {
            "N": "42"
          },
          "unit_price": {
            "N": "14.0"
          },
          "quantity": {
            "N": "20"
          },
          "discount": {
            "N": "0.0"
          }
        }
      }
    },
    {
      "PutRequest": {
        "Item": {
          "order_id": {
            "N": "10653"
          },
          "product_id": {
            "N": "16"
          },
          "unit_price": {
            "N": "17.4500008"
          },
          "quantity": {
            "N": "30"
          },
          "discount": {
            "N": "0.100000001"
          }
        }
      }
    },
    {
      "PutRequest": {
        "Item": {
          "order_id": {
            "N": "10653"
          },
          "product_id": {
            "N": "60"
          },
          "unit_price": {
            "N": "34.0"
          },
          "quantity": {
            "N": "20"
          },
          "discount": {
            "N": "0.100000001"
          }
        }
      }
    },
    {
      "PutRequest": {
        "Item": {
          "order_id": {
            "N": "10654"
          },
          "product_id": {
            "N": "4"
          },
          "unit_price": {
            "N": "22.0"
          },
          "quantity": {
            "N": "12"
          },
          "discount": {
            "N": "0.100000001"
          }
        }
      }
    },
    {
      "PutRequest": {
        "Item": {
          "order_id": {
            "N": "10654"
          },
          "product_id": {
            "N": "39"
          },
          "unit_price": {
            "N": "18.0"
          },
          "quantity": {
            "N": "20"
          },
          "discount": {
            "N": "0.100000001"
          }
        }
      }
    },
    {
      "PutRequest": {
        "Item": {
          "order_id": {
            "N": "10654"
          },
          "product_id": {
            "N": "54"
          },
          "unit_price": {
            "N": "7.44999981"
          },
          "quantity": {
            "N": "6"
          },
          "discount": {
            "N": "0.100000001"
          }
        }
      }
    },
    {
      "PutRequest": {
        "Item": {
          "order_id": {
            "N": "10655"
          },
          "product_id": {
            "N": "41"
          },
          "unit_price": {
            "N": "9.64999962"
          },
          "quantity": {
            "N": "20"
          },
          "discount": {
            "N": "0.200000003"
          }
        }
      }
    },
    {
      "PutRequest": {
        "Item": {
          "order_id": {
            "N": "10656"
          },
          "product_id": {
            "N": "14"
          },
          "unit_price": {
            "N": "23.25"
          },
          "quantity": {
            "N": "3"
          },
          "discount": {
            "N": "0.100000001"
          }
        }
      }
    },
    {
      "PutRequest": {
        "Item": {
          "order_id": {
            "N": "10656"
          },
          "product_id": {
            "N": "44"
          },
          "unit_price": {
            "N": "19.4500008"
          },
          "quantity": {
            "N": "28"
          },
          "discount": {
            "N": "0.100000001"
          }
        }
      }
    },
    {
      "PutRequest": {
        "Item": {
          "order_id": {
            "N": "10656"
          },
          "product_id": {
            "N": "47"
          },
          "unit_price": {
            "N": "9.5"
          },
          "quantity": {
            "N": "6"
          },
          "discount": {
            "N": "0.100000001"
          }
        }
      }
    },
    {
      "PutRequest": {
        "Item": {
          "order_id": {
            "N": "10657"
          },
          "product_id": {
            "N": "15"
          },
          "unit_price": {
            "N": "15.5"
          },
          "quantity": {
            "N": "50"
          },
          "discount": {
            "N": "0.0"
          }
        }
      }
    },
    {
      "PutRequest": {
        "Item": {
          "order_id": {
            "N": "10657"
          },
          "product_id": {
            "N": "41"
          },
          "unit_price": {
            "N": "9.64999962"
          },
          "quantity": {
            "N": "24"
          },
          "discount": {
            "N": "0.0"
          }
        }
      }
    }
  ]
}